setup.py
bin/starsheep
bin/starsheep-cli
starsheep/__init__.py
starsheep/command_line.py
starsheep/context.py
starsheep.egg-info/PKG-INFO
starsheep.egg-info/SOURCES.txt
starsheep.egg-info/dependency_links.txt
starsheep.egg-info/requires.txt
starsheep.egg-info/top_level.txt
starsheep/listeners/__init__.py
starsheep/listeners/listener.py
starsheep/listeners/reject_listener.py
starsheep/listeners/script_listener.py
starsheep/listeners/update_listener.py
starsheep/models/__init__.py
starsheep/models/model.py
starsheep/scripts/__init__.py
starsheep/scripts/script.py
starsheep/variables/__init__.py
starsheep/variables/cmdline_variable.py
starsheep/variables/context_variable.py
starsheep/variables/model_vairable.py
starsheep/variables/script_vairable.py
starsheep/variables/static_variable.py
starsheep/variables/variable.py