Metadata-Version: 2.1
Name: starsheep
Version: 0.8
Summary: Starsheep YAML interpreter
Home-page: https://starsheep.io
Author: Maciej Nabozny
Author-email: contact@cloudover.io
License: UNKNOWN
Platform: UNKNOWN
Classifier: Programming Language :: Python :: 3
Classifier: License :: OSI Approved :: MIT License
Classifier: Operating System :: OS Independent
Requires-Python: >=3.5
